darkbin.py
darkbin-0.4.0.dist-info/METADATA
darkbin-0.4.0.dist-info/WHEEL
darkbin-0.4.0.dist-info/entry_points.txt
darkbin-0.4.0.dist-info/top_level.txt
darkbin-0.4.0.dist-info/RECORD
