Metadata-Version: 2.1
Name: darkbin
Version: 0.4.0
Summary: Darkbin updated version
Home-page: https://github.com/yourusername/darkbin
Author: Your Name
Author-email: you@example.com
Classifier: Programming Language :: Python :: 3
Classifier: License :: OSI Approved :: MIT License
Classifier: Operating System :: OS Independent
Requires-Python: >=3.7
